pylab/Unit.py
pylab/__init__.py
venturelab-0.0.1.dist-info/LICENCE
venturelab-0.0.1.dist-info/METADATA
venturelab-0.0.1.dist-info/WHEEL
venturelab-0.0.1.dist-info/top_level.txt
venturelab-0.0.1.dist-info/RECORD
