Metadata-Version: 2.1
Name: venturelab
Version: 0.0.1
Summary: A Python Lab Experiments And Testing Library
Home-page: https://penshellpenos.web.app
Author: Aryan Thakur
Author-email: aryan.aparna.thakur@gmail.com
License: UNKNOWN
Platform: UNKNOWN
Classifier: Programming Language :: Python :: 3
Classifier: License :: OSI Approved :: MIT License
Classifier: Operating System :: OS Independent
Requires-Python: >=3.7
